{
  "date": "2026-07-10",
  "compared_to": "2026-07-09",
  "added_count": 86,
  "removed_count": 133,
  "added": [
    {
      "title": "Senior Corporate Communications Lead",
      "url": "https://polestar.teamtailor.com/jobs/8015692-senior-corporate-communications-lead",
      "location": "",
      "company": "Polestar",
      "country": "SE",
      "tier": "scale"
    },
    {
      "title": "Vikariat rettighetsforvalter VG+ Sport (12 mnd, intern utlysning)",
      "url": "https://schibsted.teamtailor.com/no/jobs/8042076-vikariat-rettighetsforvalter-vg-sport-12-mnd-intern-utlysning",
      "location": "",
      "company": "Schibsted",
      "country": "SE",
      "tier": "scale"
    },
    {
      "title": "Customer Support Representative (Danish Speaking)",
      "url": "https://jobs.storytel.com/jobs/8046540-customer-support-representative-danish-speaking",
      "location": "",
      "company": "Storytel",
      "country": "SE",
      "tier": "scale"
    },
    {
      "title": "Workforce Planner, Sweden",
      "url": "https://jobs.ashbyhq.com/neko-health/015d09c9-06f8-4920-86b9-12ce25e6fe55",
      "location": "Stockholm",
      "company": "Neko Health",
      "country": "SE",
      "tier": "growth"
    },
    {
      "title": "Operations Intern (m/f/d)",
      "url": "https://careers.voi.com/jobs/8030365-operations-intern-m-f-d",
      "location": "",
      "company": "Voi",
      "country": "SE",
      "tier": "growth"
    },
    {
      "title": "Talent Acquisition Representative - FTC (m/f/d)",
      "url": "https://careers.voi.com/jobs/7994238-talent-acquisition-representative-ftc-m-f-d",
      "location": "",
      "company": "Voi",
      "country": "SE",
      "tier": "growth"
    },
    {
      "title": "Talent Acquisition Representative - FTC (m/f/d)",
      "url": "https://careers.voi.com/jobs/7846622-talent-acquisition-representative-ftc-m-f-d",
      "location": "",
      "company": "Voi",
      "country": "SE",
      "tier": "growth"
    },
    {
      "title": "Fleet Specialist - Driver/Fahrer (m/w/d)",
      "url": "https://careers.voi.com/jobs/8051520-fleet-specialist-driver-fahrer-m-w-d",
      "location": "",
      "company": "Voi",
      "country": "SE",
      "tier": "growth"
    },
    {
      "title": "Heat Pump Installer",
      "url": "https://career.airahome.com/jobs/8052508-heat-pump-installer",
      "location": "",
      "company": "Aira",
      "country": "SE",
      "tier": "early"
    },
    {
      "title": "Heat Pump Installer",
      "url": "https://career.airahome.com/jobs/8052501-heat-pump-installer",
      "location": "",
      "company": "Aira",
      "country": "SE",
      "tier": "early"
    },
    {
      "title": "Plumbing and Heating Engineer",
      "url": "https://career.airahome.com/jobs/8051347-plumbing-and-heating-engineer",
      "location": "",
      "company": "Aira",
      "country": "SE",
      "tier": "early"
    },
    {
      "title": "Plumbing and Heating Engineer",
      "url": "https://career.airahome.com/jobs/8051335-plumbing-and-heating-engineer",
      "location": "",
      "company": "Aira",
      "country": "SE",
      "tier": "early"
    },
    {
      "title": "Plumbing and Heating Engineer",
      "url": "https://career.airahome.com/jobs/8051317-plumbing-and-heating-engineer",
      "location": "",
      "company": "Aira",
      "country": "SE",
      "tier": "early"
    },
    {
      "title": "Senior Software Engineer",
      "url": "https://jobs.ashbyhq.com/kognity/41ab694a-a225-461c-8507-d346a05201ff",
      "location": "Sweden",
      "company": "Kognity",
      "country": "SE",
      "tier": "early"
    },
    {
      "title": "Senior Operations Manager, ESG & Sustainability",
      "url": "https://jobs.ashbyhq.com/legora/56c298d6-6fab-4752-a8db-596b6cc86f9e",
      "location": "Stockholm HQ",
      "company": "Legora",
      "country": "SE",
      "tier": "early"
    },
    {
      "title": "Legal Engineer - Tax",
      "url": "https://jobs.ashbyhq.com/legora/b0f904af-541e-4dbd-9ffe-0acbc5e524f7",
      "location": "Houston",
      "company": "Legora",
      "country": "SE",
      "tier": "early"
    },
    {
      "title": "Legal Engineer - Tax",
      "url": "https://jobs.ashbyhq.com/legora/d2305991-5616-445f-a57c-1331e47090ed",
      "location": "Denver",
      "company": "Legora",
      "country": "SE",
      "tier": "early"
    },
    {
      "title": "Facility Management Team Lead",
      "url": "https://jobs.ashbyhq.com/iceye/50ea94b9-1799-49ed-98f2-fdf29bf4fef8",
      "location": "Espoo",
      "company": "ICEYE",
      "country": "FI",
      "tier": "scale"
    },
    {
      "title": "Business Consultant/Solution Consultant (Japanese and English Speaking)",
      "url": "https://www.relexsolutions.com/careers/jobs/business-consultant-solution-consultant-japanese-and-english-speaking/",
      "location": "",
      "company": "RELEX Solutions",
      "country": "FI",
      "tier": "scale"
    },
    {
      "title": "Senior Data Scientist, Consumer Core",
      "url": "https://careers.wolt.com/jobs/1/8051073",
      "location": "",
      "company": "Wolt",
      "country": "FI",
      "tier": "scale"
    },
    {
      "title": "Support Associate (Full Time)",
      "url": "https://careers.wolt.com/jobs/1/6693465",
      "location": "",
      "company": "Wolt",
      "country": "FI",
      "tier": "scale"
    },
    {
      "title": "Senior Technical Support Engineer",
      "url": "https://jobs.lever.co/frontify/0c917de7-1937-4778-9b69-b138cbccd8d5",
      "location": "SANKT GALLEN METROPOLITAN AREA",
      "company": "Frontify Finland",
      "country": "FI",
      "tier": "growth"
    },
    {
      "title": "Senior Fullstack Developer",
      "url": "https://jobs.ashbyhq.com/reaktor/c73fe87b-85a5-4af9-8e43-d9f02f3bd541",
      "location": "Helsinki",
      "company": "Reaktor",
      "country": "FI",
      "tier": "growth"
    },
    {
      "title": "Software Engineer, Defence & Security",
      "url": "https://jobs.ashbyhq.com/reaktor/abd34165-dbf8-4d32-83c3-2b2d5b76f026",
      "location": "Helsinki",
      "company": "Reaktor",
      "country": "FI",
      "tier": "growth"
    },
    {
      "title": "Commercial Planning Manager",
      "url": "https://careers.swappie.com/jobs/7633349-commercial-planning-manager",
      "location": "",
      "company": "Swappie",
      "country": "FI",
      "tier": "growth"
    },
    {
      "title": "Senior Ground Software Engineer",
      "url": "https://careers.reorbit.space/jobs/7189745-senior-ground-software-engineer",
      "location": "",
      "company": "ReOrbit",
      "country": "FI",
      "tier": "early"
    },
    {
      "title": "Senior Data Analyst",
      "url": "https://careers-no.itera.com/jobs/8050319-senior-data-analyst",
      "location": "",
      "company": "Itera",
      "country": "NO",
      "tier": "growth"
    },
    {
      "title": "Senior Data Engineer",
      "url": "https://careers-no.itera.com/jobs/8050121-senior-data-engineer",
      "location": "",
      "company": "Itera",
      "country": "NO",
      "tier": "growth"
    },
    {
      "title": "Vikariat rettighetsforvalter VG+ Sport (12 mnd, intern utlysning)",
      "url": "https://schibsted.teamtailor.com/no/jobs/8042076-vikariat-rettighetsforvalter-vg-sport-12-mnd-intern-utlysning",
      "location": "",
      "company": "Schibsted Norway",
      "country": "NO",
      "tier": "growth"
    },
    {
      "title": "Office Ambassador (1 year fixed term contract, ...",
      "url": "https://jobs.lunar.app/jobs/8028944-office-ambassador-1-year-fixed-term-contract-hourly-paid",
      "location": "",
      "company": "Lunar Way",
      "country": "DK",
      "tier": "growth"
    },
    {
      "title": "Devops Engineer",
      "url": "https://careers.adcash.com/jobs/7725646-devops-engineer",
      "location": "",
      "company": "Adcash",
      "country": "EE",
      "tier": "early"
    },
    {
      "title": "Software Engineer",
      "url": "https://www.aplitrak.com/?adid=am9sc3Nvbi40MzExNy4xMzc2NUBzYWFiLmFwbGl0cmFrLmNvbQ",
      "location": "Göteborg",
      "company": "Combitech Aktiebolag",
      "country": "SE",
      "tier": "aggregator",
      "source": "jobtech"
    },
    {
      "title": "Software Engineer - Developer Experience",
      "url": "https://ats.talentadore.com/apply/software-engineer-developer-experience/ZnWOgK",
      "location": "Göteborg",
      "company": "INFOTIV AB",
      "country": "SE",
      "tier": "aggregator",
      "source": "jobtech"
    },
    {
      "title": "Lead Engineer, Photonics IC Software Design",
      "url": "https://www.linkedin.com/jobs/view/4431772098/",
      "location": "Stockholm",
      "company": "II-VI Järfälla AB",
      "country": "SE",
      "tier": "aggregator",
      "source": "jobtech"
    },
    {
      "title": "Senior Software Engineer",
      "url": "https://jobs.ashbyhq.com/kognity/41ab694a-a225-461c-8507-d346a05201ff",
      "location": "Stockholm",
      "company": "Kognity AB",
      "country": "SE",
      "tier": "aggregator",
      "source": "jobtech"
    },
    {
      "title": "Senior .NET Developer för produktbolag",
      "url": "https://jobs.jobshark.eu/jobs/senior-software-developer-3?utm_medium=platsbanken_advertising&amp;utm_campaign=platsbanken_referral&amp;utm_id=platsbanken",
      "location": "Arboga",
      "company": "Comstream AB",
      "country": "SE",
      "tier": "aggregator",
      "source": "jobtech"
    },
    {
      "title": "Senior iOS Developer för produktbolag",
      "url": "https://jobs.jobshark.eu/jobs/senior-ios-developer?utm_medium=platsbanken_advertising&amp;utm_campaign=platsbanken_referral&amp;utm_id=platsbanken",
      "location": "Arboga",
      "company": "Comstream AB",
      "country": "SE",
      "tier": "aggregator",
      "source": "jobtech"
    },
    {
      "title": "Mobile App Developer Android för produktbolag",
      "url": "https://jobs.jobshark.eu/jobs/mobile-app-developer-android?utm_medium=platsbanken_advertising&amp;utm_campaign=platsbanken_referral&amp;utm_id=platsbanken",
      "location": "Arboga",
      "company": "Comstream AB",
      "country": "SE",
      "tier": "aggregator",
      "source": "jobtech"
    },
    {
      "title": ".NET Senior System Developer",
      "url": "https://candidate.hr-manager.net/ApplicationInit.aspx?cid=374&ProjectId=192797&DepartmentId=16449&MediaId=5598&utm_medium=talentech_publishing&utm_source=jobtip",
      "location": "Solna",
      "company": "Nobina Sverige AB",
      "country": "SE",
      "tier": "aggregator",
      "source": "jobtech"
    },
    {
      "title": "Senior Platform Engineer / DevOps Consultant to Malmö!",
      "url": "https://www.academicwork.se/lediga-jobb/p/platsbanken/8QOS01",
      "location": "Malmö",
      "company": "ACADEMIC WORK SWEDEN AB",
      "country": "SE",
      "tier": "aggregator",
      "source": "jobtech"
    },
    {
      "title": "Senior Genesys Developer",
      "url": "https://jobs.avaron.se/jobs/8048479-senior-genesys-developer/applications/new?promotion=2095406-arbetsformedlingen",
      "location": "Stockholm",
      "company": "Avaron AB",
      "country": "SE",
      "tier": "aggregator",
      "source": "jobtech"
    },
    {
      "title": "Full Stack Developer - Antrino Labs",
      "url": "https://arbetsformedlingen.se/platsbanken/annonser/31263267",
      "location": "Stockholm",
      "company": "Preventai AB",
      "country": "SE",
      "tier": "aggregator",
      "source": "jobtech"
    },
    {
      "title": "Entry Level: Radio Algorithm Developer",
      "url": "https://ericsson-ab.contactrh.com/jobs/9669/44303711",
      "location": "Lund",
      "company": "ERICSSON AB",
      "country": "SE",
      "tier": "aggregator",
      "source": "jobtech"
    },
    {
      "title": "Senior Genesys Cloud Developer  18527",
      "url": "https://veritaz.se/jobs/senior-genesys-cloud-developer-18527/",
      "location": "",
      "company": "Veritaz AB",
      "country": "SE",
      "tier": "aggregator",
      "source": "jobtech"
    },
    {
      "title": "Backend Developer",
      "url": "https://jobs.validio.io/jobs",
      "location": "Stockholm",
      "company": "Validio AB",
      "country": "SE",
      "tier": "aggregator",
      "source": "jobtech"
    },
    {
      "title": "Senior Data Engineer – Oncology Analytics Platform",
      "url": "https://www.raysearchlabs.com/career/?jobid=315787&ref=platsbankenv2",
      "location": "Stockholm",
      "company": "RaySearch Laboratories AB (publ)",
      "country": "SE",
      "tier": "aggregator",
      "source": "jobtech"
    },
    {
      "title": " Data Engineer - Data & AI Foundation - Cibes Lift Group",
      "url": "https://www.aplitrak.com/?adid=bWFyamNhLjU4MjAyLjEzNzY1QG1hbnBvd2VyZ3JvdXBub3JkaWNzLmFwbGl0cmFrLmNvbQ",
      "location": "Gävle",
      "company": "Experis AB",
      "country": "SE",
      "tier": "aggregator",
      "source": "jobtech"
    },
    {
      "title": "MSCA-doktorand inom SecReSy4You-nätverket",
      "url": "https://uu.varbi.com/se/what:job/jobID:951537/type:job/where:125/apply:1",
      "location": "Uppsala",
      "company": "UPPSALA UNIVERSITET",
      "country": "SE",
      "tier": "aggregator",
      "source": "jobtech"
    },
    {
      "title": "Forskningsingenjör",
      "url": "https://lu.varbi.com/se/what:job/jobID:952069/type:job/where:125/apply:1",
      "location": "Lund",
      "company": "LUNDS UNIVERSITET",
      "country": "SE",
      "tier": "aggregator",
      "source": "jobtech"
    },
    {
      "title": "Senior Singleview DevOps Engineer",
      "url": "https://jobs.avaron.se/jobs/8051164-senior-singleview-devops-engineer/applications/new?promotion=2096107-arbetsformedlingen",
      "location": "Stockholm",
      "company": "Avaron AB",
      "country": "SE",
      "tier": "aggregator",
      "source": "jobtech"
    },
    {
      "title": "Azure DevOps Specialist",
      "url": "https://jobs.avaron.se/jobs/8047254-azure-devops-specialist/applications/new?promotion=2095018-arbetsformedlingen",
      "location": "Stockholm",
      "company": "Avaron AB",
      "country": "SE",
      "tier": "aggregator",
      "source": "jobtech"
    },
    {
      "title": "Daily Operations Manager (Interim)",
      "url": "https://pnty-apply.ponty-system.se/novarebemanning?id=1230&pnty_src=platsbanken",
      "location": "Göteborg",
      "company": "Novare Bemanning AB",
      "country": "SE",
      "tier": "aggregator",
      "source": "jobtech"
    },
    {
      "title": "Regular Test Engineer",
      "url": "https://arbetsformedlingen.se/platsbanken/annonser/31265149",
      "location": "Göteborg",
      "company": "Luxoft Sweden AB",
      "country": "SE",
      "tier": "aggregator",
      "source": "jobtech"
    },
    {
      "title": "Environmental Liability Project Manager - Europe",
      "url": "https://career5.successfactors.eu/sfcareer/jobreqcareer?jobId=14375&company=nouryonP",
      "location": "Göteborg",
      "company": "Nouryon Functional Chemicals AB",
      "country": "SE",
      "tier": "aggregator",
      "source": "jobtech"
    },
    {
      "title": "Project Controls Associate",
      "url": "https://arbetsformedlingen.se/platsbanken/annonser/31264956",
      "location": "",
      "company": "CO-WORKER TECHNOLOGY SWEDEN AB",
      "country": "SE",
      "tier": "aggregator",
      "source": "jobtech"
    },
    {
      "title": "Operations Manager (Workplace supervisor)",
      "url": "https://se.sodexo.com/jobba-hos-oss/lediga-jobb?rmpage=job&rmjob=9038&utm_medium=talentech_publishing&utm_source=jobtip",
      "location": "Stockholm",
      "company": "Sodexo AB",
      "country": "SE",
      "tier": "aggregator",
      "source": "jobtech"
    },
    {
      "title": "Audiovisual Installation & Operations Coordinator",
      "url": "https://careers.cern/jobs/sce-sg-tf-2026-143-ld/",
      "location": "",
      "company": "CERN",
      "country": "SE",
      "tier": "aggregator",
      "source": "jobtech"
    },
    {
      "title": "IT Object Leader - Surface Ship",
      "url": "https://www.aplitrak.com/?adid=ai5hbmRlcmJlcmcuMzc5NjcuMTM3NjVAc2FhYi5hcGxpdHJhay5jb20",
      "location": "Karlskrona",
      "company": "SAAB AKTIEBOLAG",
      "country": "SE",
      "tier": "aggregator",
      "source": "jobtech"
    },
    {
      "title": "Junior Project Document Controller - Engineering",
      "url": "https://ars2.equest.com/?response_id=3e3518702f1c4f3bc59e7aa74834e170",
      "location": "Göteborg",
      "company": "Zeppelin Sverige AB",
      "country": "SE",
      "tier": "aggregator",
      "source": "jobtech"
    },
    {
      "title": "Logistics Manager - Expat in Saudi Arabia",
      "url": "https://www.aplitrak.com/?adid=c2ltb24ucGV0dGVyc3Nvbi40MzIwOS4xMzc2NUBzYWFiLmFwbGl0cmFrLmNvbQ",
      "location": "Linköping",
      "company": "SAAB AKTIEBOLAG",
      "country": "SE",
      "tier": "aggregator",
      "source": "jobtech"
    },
    {
      "title": "Project Supplier Quality Manager ",
      "url": "https://www.unikresurs.se/lediga-tjanster/?mtrpage=assignment&mtrt=ams&mtrid=9768",
      "location": "Finspång",
      "company": "UNIK Resurs i Sverige AB",
      "country": "SE",
      "tier": "aggregator",
      "source": "jobtech"
    },
    {
      "title": "Sales Engineer",
      "url": "https://www.valmet.com/careers/?country=sweden&primarylocation=sundsvall",
      "location": "Sundsvall",
      "company": "Valmet Aktiebolag",
      "country": "SE",
      "tier": "aggregator",
      "source": "jobtech"
    },
    {
      "title": "Chief Engineer - SW Uptime & Quality",
      "url": "https://career5.successfactors.eu/sfcareer/jobreqcareerpvt?jobId=28664&company=volkswagenP20&st=CAF3A8972880B9BFD523A91EA2626685CBB54F6F",
      "location": "Södertälje",
      "company": "SCANIA CV AKTIEBOLAG",
      "country": "SE",
      "tier": "aggregator",
      "source": "jobtech"
    },
    {
      "title": "Cyber Security Tester",
      "url": "https://jobs.scania.com/job/S%C3%B6dert%C3%A4lje-Cyber-Security-Tester-151-38/1401698633/",
      "location": "Södertälje",
      "company": "SCANIA CV AKTIEBOLAG",
      "country": "SE",
      "tier": "aggregator",
      "source": "jobtech"
    },
    {
      "title": "SAP S/4 Analyst II",
      "url": "https://jobs.tetrapak.com/job/SAP-S4-Analyst-II/99757-en_GB/",
      "location": "Lund",
      "company": "AKTIEBOLAGET TETRA PAK",
      "country": "SE",
      "tier": "aggregator",
      "source": "jobtech"
    },
    {
      "title": "Manager Verification & Test to Beyond Gravity Linköping",
      "url": "https://careers.beyondgravity.com/BeyondGravity/job/Link%C3%B6ping-Manager-Verification-&-Test/1413277733/",
      "location": "Linköping",
      "company": "Beyond Gravity Sweden AB",
      "country": "SE",
      "tier": "aggregator",
      "source": "jobtech"
    },
    {
      "title": "Contract Engineer – Large Projects & Electrification",
      "url": "https://bergpropulsion.teamtailor.com/jobs/7897262-contract-engineer-large-projects-electrification/applications/new?promotion=2095091-arbetsformedlingen",
      "location": "Öckerö",
      "company": "Berg Propulsion Production AB",
      "country": "SE",
      "tier": "aggregator",
      "source": "jobtech"
    },
    {
      "title": "Security & Infrastructure Engineer",
      "url": "https://career.naturalcycles.com/jobs/8002329-security-infrastructure-engineer/applications/new?promotion=2095076-arbetsformedlingen",
      "location": "Stockholm",
      "company": "NaturalCycles Nordic AB",
      "country": "SE",
      "tier": "aggregator",
      "source": "jobtech"
    },
    {
      "title": "Hemstädare Märsta - Hemfrid",
      "url": "https://karriar.hemfrid.se/jobs/7725434-hemstadare-marsta-hemfrid/applications/new?promotion=2094833-arbetsformedlingen",
      "location": "Upplands Väsby",
      "company": "Hemfrid i Sverige AB",
      "country": "SE",
      "tier": "aggregator",
      "source": "jobtech"
    },
    {
      "title": "General Worker (Disk)",
      "url": "https://arbetsformedlingen.se/platsbanken/annonser/31262346",
      "location": "Sigtuna",
      "company": "NEWREST INFLIGHT SWEDEN AB",
      "country": "SE",
      "tier": "aggregator",
      "source": "jobtech"
    },
    {
      "title": "Lead Consultant (OpenShift) | Gothenburg",
      "url": "https://digitalcareers.infosys.com/global-careers/company-job/description/reqid/149325BR",
      "location": "Stockholm",
      "company": "Infosys Technologies (Sweden) AB",
      "country": "SE",
      "tier": "aggregator",
      "source": "jobtech"
    },
    {
      "title": "Production Manager till vårt uppdrag på e-apoteket i Eskilstuna",
      "url": "https://jobb.insitepart.se/jobs/7055241-production-manager-till-vart-uppdrag-pa-e-apoteket-i-eskilstuna/applications/new?promotion=2094558-arbetsformedlingen",
      "location": "Eskilstuna",
      "company": "Insitepart AB",
      "country": "SE",
      "tier": "aggregator",
      "source": "jobtech"
    },
    {
      "title": "Junior Project Controls Associate",
      "url": "https://jobs.avaron.se/jobs/8044642-junior-project-controls-associate/applications/new?promotion=2094464-arbetsformedlingen",
      "location": "Boden",
      "company": "Avaron AB",
      "country": "SE",
      "tier": "aggregator",
      "source": "jobtech"
    },
    {
      "title": "Product System Security Engineer Giraffe xA",
      "url": "https://www.aplitrak.com/?adid=cy5qdW5nZXZpLjY1OTA4LjEzNzY1QHNhYWIuYXBsaXRyYWsuY29t",
      "location": "Göteborg",
      "company": "SAAB AKTIEBOLAG",
      "country": "SE",
      "tier": "aggregator",
      "source": "jobtech"
    },
    {
      "title": "Postdoctoral Researcher in Computational Social Science",
      "url": "https://web103.reachmee.com/ext/I017/1114/main?site=6&validator=107666e3b6b77a48547b7422cbb04714&lang=SE&rmpage=job&rmjob=15112&utm_medium=talentech_publishing&utm_source=jobtip",
      "location": "Uppsala",
      "company": "SVERIGES LANTBRUKSUNIVERSITET",
      "country": "SE",
      "tier": "aggregator",
      "source": "jobtech"
    },
    {
      "title": "Webbutvecklare",
      "url": "https://jobbify.se/job/t4iaa7xn1gp45bqhz/",
      "location": "Jönköping",
      "company": "Hirely AB",
      "country": "SE",
      "tier": "aggregator",
      "source": "jobtech"
    },
    {
      "title": "Frontendutvecklare | Linköping",
      "url": "https://pnty-apply.ponty-system.se/jobway?id=5598&pnty_src=platsbanken",
      "location": "Lidköping",
      "company": "Jobway AB",
      "country": "SE",
      "tier": "aggregator",
      "source": "jobtech"
    },
    {
      "title": "Website Development Intern",
      "url": "https://itsbirger.com/careers",
      "location": "",
      "company": "Birger AB",
      "country": "SE",
      "tier": "aggregator",
      "source": "jobtech"
    },
    {
      "title": "Product Marketing Manager  GTM specialist",
      "url": "https://careers.abax.com/jobs/8051604-product-marketing-manager-gtm-specialist/ab9cfa14-349d-47e3-bc7f-6ce99721b4a5",
      "location": "Stockholm",
      "company": "ABAX Sweden AB",
      "country": "SE",
      "tier": "aggregator",
      "source": "jobtech"
    },
    {
      "title": "Receptionist Haymarket by Scandic, deltid  20%. Helgjobb",
      "url": "https://easyapply.jobs/r/GIcZ2rG26PfsZG6BJCN",
      "location": "Stockholm",
      "company": "Scandic Hotels Aktiebolag",
      "country": "SE",
      "tier": "aggregator",
      "source": "jobtech"
    },
    {
      "title": "Receptionist Haymarket by Scandic, heltid",
      "url": "https://easyapply.jobs/r/UHcYu0U26OfkNUjrOxn",
      "location": "Stockholm",
      "company": "Scandic Hotels Aktiebolag",
      "country": "SE",
      "tier": "aggregator",
      "source": "jobtech"
    },
    {
      "title": "Senior System Designer / Solution Architect – Automotive & Connectivity",
      "url": "https://careers.consat.se/jobs/8051242-senior-system-designer-solution-architect-automotive-connectivity/applications/new?promotion=2096114-arbetsformedlingen",
      "location": "Göteborg",
      "company": "Consat Digital Solutions AB",
      "country": "SE",
      "tier": "aggregator",
      "source": "jobtech"
    },
    {
      "title": "Nätverkstekniker med fokus på NSX och Data Fabric",
      "url": "https://recruit.visma.com/spa/public/apply?guidAssignment=bf0ec44e-06a1-4c1a-b476-86c32b78c047&publishCode=PB&TK=ebecbedc-82a6-4940-aca0-66b93c128418",
      "location": "Örebro",
      "company": "STATISTISKA CENTRALBYRÅN",
      "country": "SE",
      "tier": "aggregator",
      "source": "jobtech"
    },
    {
      "title": "SAP Public Cloud-konsult till SEIDOR Nordics, Göteborg",
      "url": "https://jobb.effektiv.se/jobs/8047698-sap-public-cloud-konsult-till-seidor-nordics-goteborg?promotion=2095371-arbetsformedlingen",
      "location": "Göteborg",
      "company": "AB Effektiv Väst",
      "country": "SE",
      "tier": "aggregator",
      "source": "jobtech"
    },
    {
      "title": "Cloud Architect inom Google Cloud",
      "url": "https://www.nordicrule.se/jobs/45-cloud-architect-inom-google-cloud/?pnty_src=platsbanken",
      "location": "Stockholm",
      "company": "Nordicrule AB",
      "country": "SE",
      "tier": "aggregator",
      "source": "jobtech"
    },
    {
      "title": "Nattreceptionist till hotell i Stockholm",
      "url": "https://www.recruto.se/apps/listings/view/id/94039/tracking/5",
      "location": "Stockholm",
      "company": "Top Solution Security Sverige AB",
      "country": "SE",
      "tier": "aggregator",
      "source": "jobtech"
    }
  ],
  "removed": [
    {
      "title": "Market Development Manager",
      "url": "https://polestar.teamtailor.com/jobs/7512193-market-development-manager",
      "location": "",
      "company": "Polestar",
      "country": "SE",
      "tier": "scale"
    },
    {
      "title": "Senior UX Manager til Schibsted: Led mennesker gjennom AI-transformasjonen av UX",
      "url": "https://schibsted.teamtailor.com/no/jobs/7834262-senior-ux-manager-til-schibsted-led-mennesker-gjennom-ai-transformasjonen-av-ux",
      "location": "",
      "company": "Schibsted",
      "country": "SE",
      "tier": "scale"
    },
    {
      "title": "Senior Backend Engineer - Podcast",
      "url": "https://jobs.lever.co/spotify/59b1f965-f478-4e95-ae21-1a1bd4c80ff2",
      "location": "UNITED STATES OF AMERICA (HOME MIX)",
      "company": "Spotify",
      "country": "SE",
      "tier": "scale"
    },
    {
      "title": "Cardiologist ",
      "url": "https://jobs.ashbyhq.com/neko-health/91073062-edff-423e-91ce-ef0a70cf538b",
      "location": "Remote",
      "company": "Neko Health",
      "country": "SE",
      "tier": "growth"
    },
    {
      "title": "Läkare (Doctor)",
      "url": "https://jobs.ashbyhq.com/neko-health/c7171743-7f68-4b83-b727-74e5021281a3",
      "location": "Stockholm",
      "company": "Neko Health",
      "country": "SE",
      "tier": "growth"
    },
    {
      "title": "Undersköterska (Medical Operator)",
      "url": "https://jobs.ashbyhq.com/neko-health/e77ba5a8-a204-4a97-a24f-28a67598b95b",
      "location": "Stockholm",
      "company": "Neko Health",
      "country": "SE",
      "tier": "growth"
    },
    {
      "title": "Operations Intern",
      "url": "https://careers.voi.com/jobs/8030365-operations-intern",
      "location": "",
      "company": "Voi",
      "country": "SE",
      "tier": "growth"
    },
    {
      "title": "Talent Acquisition Representative - FTC",
      "url": "https://careers.voi.com/jobs/7994238-talent-acquisition-representative-ftc",
      "location": "",
      "company": "Voi",
      "country": "SE",
      "tier": "growth"
    },
    {
      "title": "Talent Acquisition Representative - FTC",
      "url": "https://careers.voi.com/jobs/7846622-talent-acquisition-representative-ftc",
      "location": "",
      "company": "Voi",
      "country": "SE",
      "tier": "growth"
    },
    {
      "title": "Fleet Specialist - Fahrer / Driver (m/f/d)",
      "url": "https://careers.voi.com/jobs/8018383-fleet-specialist-fahrer-driver-m-f-d",
      "location": "",
      "company": "Voi",
      "country": "SE",
      "tier": "growth"
    },
    {
      "title": "Plumbing and Heating Engineer",
      "url": "https://career.airahome.com/jobs/7996700-plumbing-and-heating-engineer",
      "location": "",
      "company": "Aira",
      "country": "SE",
      "tier": "early"
    },
    {
      "title": "Plumbing and Heating Engineer",
      "url": "https://career.airahome.com/jobs/7996636-plumbing-and-heating-engineer",
      "location": "",
      "company": "Aira",
      "country": "SE",
      "tier": "early"
    },
    {
      "title": "Plumbing and Heating Engineer",
      "url": "https://career.airahome.com/jobs/7773586-plumbing-and-heating-engineer",
      "location": "",
      "company": "Aira",
      "country": "SE",
      "tier": "early"
    },
    {
      "title": "Planning Agent",
      "url": "https://career.airahome.com/jobs/7769187-planning-agent",
      "location": "",
      "company": "Aira",
      "country": "SE",
      "tier": "early"
    },
    {
      "title": "Plumbing and Heating Engineer",
      "url": "https://career.airahome.com/jobs/7765311-plumbing-and-heating-engineer",
      "location": "",
      "company": "Aira",
      "country": "SE",
      "tier": "early"
    },
    {
      "title": "Head of BESS Development",
      "url": "https://flower.teamtailor.com/jobs/7784375-head-of-bess-development",
      "location": "",
      "company": "Flower",
      "country": "SE",
      "tier": "early"
    },
    {
      "title": "Performance Marketing Specialist",
      "url": "https://jobs.funnel.io/jobs/7799719-performance-marketing-specialist",
      "location": "",
      "company": "Funnel",
      "country": "SE",
      "tier": "early"
    },
    {
      "title": "Marknads- och säljansvarig",
      "url": "https://karriar.corem.se/jobs/7781825-marknads-och-saljansvarig",
      "location": "",
      "company": "Klövern",
      "country": "SE",
      "tier": "early"
    },
    {
      "title": "Sales Development Representative - Stockholm",
      "url": "https://careers.normative.io/jobs/7187431-sales-development-representative-stockholm",
      "location": "",
      "company": "Normative",
      "country": "SE",
      "tier": "early"
    },
    {
      "title": "Senior Mid-Market Account Executive, Nordic Region",
      "url": "https://careers.normative.io/jobs/2406193-senior-mid-market-account-executive-nordic-region",
      "location": "",
      "company": "Normative",
      "country": "SE",
      "tier": "early"
    },
    {
      "title": "Underwriting Representative - German Market",
      "url": "https://jobs.qred.com/jobs/7873012-underwriting-representative-german-market",
      "location": "",
      "company": "Qred",
      "country": "SE",
      "tier": "early"
    },
    {
      "title": "FPGA Engineer ",
      "url": "https://jobs.ashbyhq.com/iceye/2607e229-2dcc-4268-853c-ae080707a61b",
      "location": "Valencia",
      "company": "ICEYE",
      "country": "FI",
      "tier": "scale"
    },
    {
      "title": "Solution Engineer (m/f/*) Price & Promotions",
      "url": "https://www.relexsolutions.com/careers/jobs/solution-engineer-m-f-price-promotions/",
      "location": "",
      "company": "RELEX Solutions",
      "country": "FI",
      "tier": "scale"
    },
    {
      "title": "Key Account Manager",
      "url": "https://careers.wolt.com/jobs/1/7824126",
      "location": "",
      "company": "Wolt",
      "country": "FI",
      "tier": "scale"
    },
    {
      "title": "Sales Support Associate",
      "url": "https://careers.wolt.com/jobs/1/8034772",
      "location": "",
      "company": "Wolt",
      "country": "FI",
      "tier": "scale"
    },
    {
      "title": "English speaking Support Associate (Part-Time, Remote)",
      "url": "https://careers.wolt.com/jobs/1/7943989",
      "location": "",
      "company": "Wolt",
      "country": "FI",
      "tier": "scale"
    },
    {
      "title": "Marketing Intern – Denmark",
      "url": "https://careers.wolt.com/jobs/1/8000039",
      "location": "",
      "company": "Wolt",
      "country": "FI",
      "tier": "scale"
    },
    {
      "title": "Project Operations - Customer Support Division",
      "url": "https://careers.wolt.com/jobs/1/7988087",
      "location": "",
      "company": "Wolt",
      "country": "FI",
      "tier": "scale"
    },
    {
      "title": "German and English Speaking Support Associate (Full-time)",
      "url": "https://careers.wolt.com/jobs/1/6694796",
      "location": "",
      "company": "Wolt",
      "country": "FI",
      "tier": "scale"
    },
    {
      "title": "Store Operations Associate - Piraeus",
      "url": "https://careers.wolt.com/jobs/1/6695079",
      "location": "",
      "company": "Wolt",
      "country": "FI",
      "tier": "scale"
    },
    {
      "title": "Director, Marketplace (Denmark)",
      "url": "https://careers.wolt.com/jobs/1/7865507",
      "location": "",
      "company": "Wolt",
      "country": "FI",
      "tier": "scale"
    },
    {
      "title": "Sr. Manager, People Data AI Platform",
      "url": "https://careers.wolt.com/jobs/1/7949919",
      "location": "",
      "company": "Wolt",
      "country": "FI",
      "tier": "scale"
    },
    {
      "title": "Senior Atlassian Consultant",
      "url": "https://career.eficode.com/jobs/7858244-senior-atlassian-consultant",
      "location": "",
      "company": "Eficode",
      "country": "FI",
      "tier": "growth"
    },
    {
      "title": "Technical Project Manager",
      "url": "https://jobs.lever.co/frontify/6aa43086-d4f8-46b0-a968-9f4ec49c7bd2",
      "location": "SANKT GALLEN METROPOLITAN AREA",
      "company": "Frontify Finland",
      "country": "FI",
      "tier": "growth"
    },
    {
      "title": "QPU Development Engineer - Fixed term",
      "url": "https://iqm.teamtailor.com/jobs/7762818-qpu-development-engineer-fixed-term",
      "location": "",
      "company": "IQM Quantum",
      "country": "FI",
      "tier": "growth"
    },
    {
      "title": "Quantum Software Engineer - Qrisp",
      "url": "https://iqm.teamtailor.com/jobs/7606108-quantum-software-engineer-qrisp",
      "location": "",
      "company": "IQM Quantum",
      "country": "FI",
      "tier": "growth"
    },
    {
      "title": "Senior Treasury AnalystNew\n\nRemote - United States",
      "url": "https://job-boards.greenhouse.io/oura/jobs/4307067009",
      "location": "",
      "company": "Oura",
      "country": "FI",
      "tier": "growth"
    },
    {
      "title": "Senior Harness Engineer",
      "url": "https://careers.reorbit.space/jobs/5685551-senior-harness-engineer",
      "location": "",
      "company": "ReOrbit",
      "country": "FI",
      "tier": "early"
    },
    {
      "title": "Principal Engineer (R-19113)",
      "url": "https://jobs.lever.co/dnb/6be12fd9-968e-42e8-af7f-36339946879b",
      "location": "JACKSONVILLE - FLORIDA - UNITED STATES",
      "company": "DNB",
      "country": "NO",
      "tier": "scale"
    },
    {
      "title": "Teknologileder Itera Bergen",
      "url": "https://careers-no.itera.com/jobs/7825786-teknologileder-itera-bergen",
      "location": "",
      "company": "Itera",
      "country": "NO",
      "tier": "growth"
    },
    {
      "title": "Senior UX Manager til Schibsted: Led mennesker gjennom AI-transformasjonen av UX",
      "url": "https://schibsted.teamtailor.com/no/jobs/7834262-senior-ux-manager-til-schibsted-led-mennesker-gjennom-ai-transformasjonen-av-ux",
      "location": "",
      "company": "Schibsted Norway",
      "country": "NO",
      "tier": "growth"
    },
    {
      "title": "FCP Onboarding Specialist (Swedish speaking)",
      "url": "https://jobs.lunar.app/jobs/7948404-fcp-onboarding-specialist-swedish-speaking",
      "location": "",
      "company": "Lunar Way",
      "country": "DK",
      "tier": "growth"
    },
    {
      "title": "Sales Director [Podads]",
      "url": "https://careers.podimo.com/jobs/7950030-sales-director-podads",
      "location": "",
      "company": "Podimo",
      "country": "DK",
      "tier": "growth"
    },
    {
      "title": "Senior Web Engineer, Intake",
      "url": "https://careers.podimo.com/jobs/7929452-senior-web-engineer-intake",
      "location": "",
      "company": "Podimo",
      "country": "DK",
      "tier": "growth"
    },
    {
      "title": "Creator Manager [Podads]",
      "url": "https://careers.podimo.com/jobs/7922896-creator-manager-podads",
      "location": "",
      "company": "Podimo",
      "country": "DK",
      "tier": "growth"
    },
    {
      "title": "Legal Advisor",
      "url": "https://careers.adcash.com/jobs/7891961-legal-advisor",
      "location": "",
      "company": "Adcash",
      "country": "EE",
      "tier": "early"
    },
    {
      "title": "Social Media Specialist",
      "url": "https://careers.adcash.com/jobs/7401106-social-media-specialist",
      "location": "",
      "company": "Adcash",
      "country": "EE",
      "tier": "early"
    },
    {
      "title": "CI Software Engineer",
      "url": "https://jobs.avaron.se/jobs/8017423-ci-software-engineer/applications/new?promotion=2085270-arbetsformedlingen",
      "location": "Göteborg",
      "company": "Avaron AB",
      "country": "SE",
      "tier": "aggregator",
      "source": "jobtech"
    },
    {
      "title": "Software Verification & Validation Engineer (OBC)",
      "url": "https://avl-list-gmbh.contactrh.com/jobs/9669/44289138",
      "location": "Göteborg",
      "company": "AVL MTC MOTORTESTCENTER AB",
      "country": "SE",
      "tier": "aggregator",
      "source": "jobtech"
    },
    {
      "title": "Automotive Software Engineer - AUTOSAR BSW",
      "url": "https://avl-list-gmbh.contactrh.com/jobs/9669/44288849",
      "location": "Göteborg",
      "company": "AVL MTC MOTORTESTCENTER AB",
      "country": "SE",
      "tier": "aggregator",
      "source": "jobtech"
    },
    {
      "title": "Automotive Software Engineer - ASW (Göteborg)",
      "url": "https://avl-list-gmbh.contactrh.com/jobs/9669/44288846",
      "location": "Göteborg",
      "company": "AVL MTC MOTORTESTCENTER AB",
      "country": "SE",
      "tier": "aggregator",
      "source": "jobtech"
    },
    {
      "title": "Software Engineer - Connected Systems",
      "url": "https://avl-list-gmbh.contactrh.com/jobs/9669/44288840",
      "location": "Göteborg",
      "company": "AVL MTC MOTORTESTCENTER AB",
      "country": "SE",
      "tier": "aggregator",
      "source": "jobtech"
    },
    {
      "title": "Software Engineer med fokus på AI",
      "url": "https://pnty-apply.ponty-system.se/friday?id=4864&pnty_src=platsbanken",
      "location": "Stockholm",
      "company": "Friday Väst AB",
      "country": "SE",
      "tier": "aggregator",
      "source": "jobtech"
    },
    {
      "title": "Embedded Software Engineer",
      "url": "https://jobs.advantekgroup.com/job/470544",
      "location": "Göteborg",
      "company": "Avatron Digital West AB",
      "country": "SE",
      "tier": "aggregator",
      "source": "jobtech"
    },
    {
      "title": "Kundfokuserad mjukvaruutvecklare sökes till bolag inom flygindustrin!",
      "url": "https://pnty-apply.ponty-system.se/friday?id=4857&pnty_src=platsbanken",
      "location": "Göteborg",
      "company": "Friday Väst AB",
      "country": "SE",
      "tier": "aggregator",
      "source": "jobtech"
    },
    {
      "title": "Senior Systemutvecklare",
      "url": "https://jobb.rasulson.com/jobs/8022992-senior-systemutvecklare",
      "location": "Sundsvall",
      "company": "Rasulson Consulting AB",
      "country": "SE",
      "tier": "aggregator",
      "source": "jobtech"
    },
    {
      "title": "CNC Programmer / Cabinetmaker",
      "url": "https://arbetsformedlingen.se/platsbanken/annonser/31247082",
      "location": "",
      "company": "PN SNedkeri",
      "country": "SE",
      "tier": "aggregator",
      "source": "jobtech"
    },
    {
      "title": "Embedded-utvecklare med erfarenhet av C och C++",
      "url": "https://jobs.gigstep.se/jobs/8017182-embedded-utvecklare-med-erfarenhet-av-c-och-c/applications/new?promotion=2085257-arbetsformedlingen",
      "location": "Lund",
      "company": "Gigstep AB",
      "country": "SE",
      "tier": "aggregator",
      "source": "jobtech"
    },
    {
      "title": "Teknisk Produktägare",
      "url": "https://www.assaabloy.com/career/en/open-positions/job.46691",
      "location": "Landskrona",
      "company": "ASSA ABLOY AB",
      "country": "SE",
      "tier": "aggregator",
      "source": "jobtech"
    },
    {
      "title": "Linux & automationspecialist",
      "url": "https://web103.reachmee.com/ext/I005/333/main?site=2&validator=a75fbd88f1b2a3a49de2af9c8b7bc228&lang=SE&rmpage=job&rmjob=49891&utm_medium=talentech_publishing&utm_source=jobtip",
      "location": "Enköping",
      "company": "FÖRSVARSMAKTEN",
      "country": "SE",
      "tier": "aggregator",
      "source": "jobtech"
    },
    {
      "title": "Senior Java Fullstackutvecklare",
      "url": "https://career.accelerate-iver.com/jobs/8016885-senior-java-fullstackutvecklare/applications/new?promotion=2085050-arbetsformedlingen",
      "location": "Stockholm",
      "company": "Iver Accelerate AB",
      "country": "SE",
      "tier": "aggregator",
      "source": "jobtech"
    },
    {
      "title": "Java-utvecklare Växjö",
      "url": "https://nexergroup.teamtailor.com/jobs/7984467-java-utvecklare-vaxjo/applications/new?promotion=2084501-arbetsformedlingen",
      "location": "Växjö",
      "company": "Nexer AB",
      "country": "SE",
      "tier": "aggregator",
      "source": "jobtech"
    },
    {
      "title": "Java-utvecklare Jönköping",
      "url": "https://nexergroup.teamtailor.com/jobs/7984366-java-utvecklare-jonkoping/applications/new?promotion=2084486-arbetsformedlingen",
      "location": "Jönköping",
      "company": "Nexer AB",
      "country": "SE",
      "tier": "aggregator",
      "source": "jobtech"
    },
    {
      "title": "Java-utvecklare Karlskrona",
      "url": "https://nexergroup.teamtailor.com/jobs/7984235-java-utvecklare-karlskrona/applications/new?promotion=2083761-arbetsformedlingen",
      "location": "Karlskrona",
      "company": "Nexer AB",
      "country": "SE",
      "tier": "aggregator",
      "source": "jobtech"
    },
    {
      "title": "PLC- och Automationsingenjör – Autonoma industrifordon Linköping",
      "url": "https://nexergroup.teamtailor.com/jobs/8011765-plc-och-automationsingenjor-autonoma-industrifordon-linkoping/applications/new?promotion=2084476-arbetsformedlingen",
      "location": "Linköping",
      "company": "Nexer AB",
      "country": "SE",
      "tier": "aggregator",
      "source": "jobtech"
    },
    {
      "title": "Innovationstekniker med inriktning mot digitalisering, AI och automation",
      "url": "https://www.hb.se/Om-hogskolan/Jobba-hos-oss/Lediga-anstallningar/?rmpage=job&rmjob=4554&utm_medium=talentech_publishing&utm_source=jobtip",
      "location": "Borås",
      "company": "HÖGSKOLAN I BORÅS",
      "country": "SE",
      "tier": "aggregator",
      "source": "jobtech"
    },
    {
      "title": "Postdoktor i maskinteknik med inriktning mot kunskapsdriven optimering",
      "url": "https://www.his.se/mot-hogskolan/jobba-hos-oss/lediga-jobb/?rmpage=job&rmjob=1136&utm_medium=talentech_publishing&utm_source=jobtip",
      "location": "Skövde",
      "company": "HÖGSKOLAN I SKÖVDE",
      "country": "SE",
      "tier": "aggregator",
      "source": "jobtech"
    },
    {
      "title": "Doktorand i informationsteknologi med inr. mot AI för Industriell Robotik",
      "url": "https://www.his.se/mot-hogskolan/jobba-hos-oss/lediga-jobb/?rmpage=job&rmjob=1138&utm_medium=talentech_publishing&utm_source=jobtip",
      "location": "Skövde",
      "company": "HÖGSKOLAN I SKÖVDE",
      "country": "SE",
      "tier": "aggregator",
      "source": "jobtech"
    },
    {
      "title": "Manager Data & Analytics - Supply Chain and Operations, Lund",
      "url": "https://www.aplitrak.com/?adid=QW1hbmRhLkJqdXJzdGFtLjE4MjUxLjEzNzY1QGF4aXNjb21tcy5hcGxpdHJhay5jb20",
      "location": "Lund",
      "company": "AXIS COMMUNICATIONS AKTIEBOLAG",
      "country": "SE",
      "tier": "aggregator",
      "source": "jobtech"
    },
    {
      "title": "Senior lecturers in Electrical Engineering",
      "url": "https://web103.reachmee.com/ext/I003/354/main?site=5&validator=43a1fbd05a0e84d542a937e3454d48f8&lang=SE&rmpage=job&rmjob=12832&utm_medium=talentech_publishing&utm_source=jobtip",
      "location": "Örebro",
      "company": "ÖREBRO UNIVERSITET",
      "country": "SE",
      "tier": "aggregator",
      "source": "jobtech"
    },
    {
      "title": "Junior Test- och Utvecklingsingenjör",
      "url": "https://jobs.avaron.se/jobs/8011006-junior-test-och-utvecklingsingenjor/applications/new?promotion=2083173-arbetsformedlingen",
      "location": "Göteborg",
      "company": "Avaron AB",
      "country": "SE",
      "tier": "aggregator",
      "source": "jobtech"
    },
    {
      "title": "Computer Vision Application Engineer",
      "url": "https://jobs.avaron.se/jobs/8011010-computer-vision-application-engineer/applications/new?promotion=2083169-arbetsformedlingen",
      "location": "Lund",
      "company": "Avaron AB",
      "country": "SE",
      "tier": "aggregator",
      "source": "jobtech"
    },
    {
      "title": "Marketing & Media Analytics",
      "url": "https://career55.sapsf.eu/sfcareer/jobreqcareerpvt?jobId=31740&company=volvoinfor&st=857F37EE10AF6A1EEAC6B2A1EB375D11235F60B2",
      "location": "Göteborg",
      "company": "VOLVO BUSINESS SERVICES AKTIEBOLAG",
      "country": "SE",
      "tier": "aggregator",
      "source": "jobtech"
    },
    {
      "title": "ML Research Engineer to Klang AI",
      "url": "https://jobs.qlose.io/jobs/8006046-ml-research-engineer-to-klang-ai/applications/new?promotion=2082437-arbetsformedlingen",
      "location": "Helsingborg",
      "company": "Qlose Recruitment & Consulting AB",
      "country": "SE",
      "tier": "aggregator",
      "source": "jobtech"
    },
    {
      "title": "Postdoktor inom AI-modellering för cellbiologi, AlphaCell",
      "url": "https://kth.varbi.com/se/what:job/jobID:952471/type:job/where:125/apply:1",
      "location": "Stockholm",
      "company": "KUNGLIGA TEKNISKA HÖGSKOLAN",
      "country": "SE",
      "tier": "aggregator",
      "source": "jobtech"
    },
    {
      "title": "Dataanalytiker till Svenska Röda Korset",
      "url": "https://tng.zerolime.se/ams/?e8687344-8e6a-4ae2-8bfa-bc86a23b286a&utm_source=AMS&utm_medium=platsbanken&utm_campaign=data-och-analytics",
      "location": "Stockholm",
      "company": "TNG Group AB",
      "country": "SE",
      "tier": "aggregator",
      "source": "jobtech"
    },
    {
      "title": "Platform Engineer",
      "url": "https://career.accelerate-iver.com/jobs/8010649-platform-engineer/applications/new?promotion=2082942-arbetsformedlingen",
      "location": "Stockholm",
      "company": "Iver Accelerate AB",
      "country": "SE",
      "tier": "aggregator",
      "source": "jobtech"
    },
    {
      "title": "Senior Singleview DevOps Engineer",
      "url": "https://jobs.avaron.se/jobs/8025330-senior-singleview-devops-engineer/applications/new?promotion=2088273-arbetsformedlingen",
      "location": "Stockholm",
      "company": "Avaron AB",
      "country": "SE",
      "tier": "aggregator",
      "source": "jobtech"
    },
    {
      "title": "DevOps Engineer",
      "url": "https://ledigajobb.futuriapeople.se/jobs/8009586-devops-engineer/applications/new?promotion=2082511-arbetsformedlingen",
      "location": "Göteborg",
      "company": "Futuria People AB",
      "country": "SE",
      "tier": "aggregator",
      "source": "jobtech"
    },
    {
      "title": "Senior Linux DevOps Engineer",
      "url": "https://jobs.avaron.se/jobs/8005971-senior-linux-devops-engineer/applications/new?promotion=2081720-arbetsformedlingen",
      "location": "Stockholm",
      "company": "Avaron AB",
      "country": "SE",
      "tier": "aggregator",
      "source": "jobtech"
    },
    {
      "title": "Project Engineer RAM",
      "url": "https://hitachi.wd1.myworkdayjobs.com/hitachi/job/Ludvika-Dalarna-County-Sweden/Project-Engineer-RAM_R0131147",
      "location": "Ludvika",
      "company": "Hitachi Energy Sweden AB",
      "country": "SE",
      "tier": "aggregator",
      "source": "jobtech"
    },
    {
      "title": "Principal R&D Professional",
      "url": "https://sandvik.wd3.myworkdayjobs.com/coromant-jobs/job/Sweden-Sandviken/Principal-R-D-Professional_R0093074",
      "location": "Sandviken",
      "company": "AKTIEBOLAGET SANDVIK COROMANT",
      "country": "SE",
      "tier": "aggregator",
      "source": "jobtech"
    },
    {
      "title": "Brunnsborrare till Malmberg Borrning",
      "url": "https://apply.workspacerecruit.com/job/17829",
      "location": "Kristianstad",
      "company": "MALMBERG BORRNING AB",
      "country": "SE",
      "tier": "aggregator",
      "source": "jobtech"
    },
    {
      "title": "Footwear Technologist  H&M Kids",
      "url": "https://jobs.smartrecruiters.com/ni/HMGroup/fc339e5b-34a1-46e90-5a327d6b7e8b-footwear-technologist-h-m-kids-",
      "location": "Stockholm",
      "company": "H & M Hennes & Mauritz GBC AB",
      "country": "SE",
      "tier": "aggregator",
      "source": "jobtech"
    },
    {
      "title": "Local Division Manager  IEC Low Voltage Motors and High Power, Sweden",
      "url": "https://careers.abb/global/en/job/JR00037875/Local-Division-Manager-IEC-Low-Voltage-Motors-and-High-Power-Sweden",
      "location": "Västerås",
      "company": "ABB AB",
      "country": "SE",
      "tier": "aggregator",
      "source": "jobtech"
    },
    {
      "title": "Industrielektriker till Perstorp Specialty Chemicals",
      "url": "https://careers.perstorp.com/jobs/8021894-industrielektriker-till-perstorp-specialty-chemicals/applications/new?promotion=2087025-arbetsformedlingen",
      "location": "Perstorp",
      "company": "Perstorp Holding AB",
      "country": "SE",
      "tier": "aggregator",
      "source": "jobtech"
    },
    {
      "title": "Mechanical Lead  Sub Project Manager",
      "url": "https://sandvik.wd3.myworkdayjobs.com/sandvik-jobs/job/Sweden-Svedala/Mechanical-Lead_R0093202-1",
      "location": "Svedala",
      "company": "Sandvik Aktiebolag",
      "country": "SE",
      "tier": "aggregator",
      "source": "jobtech"
    },
    {
      "title": "Systemarkitekt IoT",
      "url": "https://www.aplitrak.com/?adid=VE1ITVMuMTU1NzMuMTM3NjVAdG95b3RhbWhlbWVhLmFwbGl0cmFrLmNvbQ",
      "location": "Mjölby",
      "company": "Toyota Material Handling Europe AB",
      "country": "SE",
      "tier": "aggregator",
      "source": "jobtech"
    },
    {
      "title": "Konstruktör Special Products",
      "url": "https://www.aplitrak.com/?adid=VE1ITVMuNjE0MTguMTM3NjVAdG95b3RhbWhlbWVhLmFwbGl0cmFrLmNvbQ",
      "location": "Mjölby",
      "company": "Toyota Material Handling Europe AB",
      "country": "SE",
      "tier": "aggregator",
      "source": "jobtech"
    },
    {
      "title": "PHINIA Sweden AB (fd SEM AB) söker en chef för projektledning.",
      "url": "https://phinia.wd5.myworkdayjobs.com/sv-SE/PHINIA_Careers/job/Amal---Sweden/Project-Manager-Lead_R2026-0516",
      "location": "Åmål",
      "company": "PHINIA Sweden AB",
      "country": "SE",
      "tier": "aggregator",
      "source": "jobtech"
    },
    {
      "title": "Supplier Quality Assurance Engineer",
      "url": "https://careers.beyondgravity.com/BeyondGravity/job/Link%C3%B6ping-Supplier-Quality-Assurance-Engineer/1411405933/",
      "location": "Linköping",
      "company": "Beyond Gravity Sweden AB",
      "country": "SE",
      "tier": "aggregator",
      "source": "jobtech"
    },
    {
      "title": "Site Maintenance Lead",
      "url": "https://ars2.equest.com/?response_id=b47d6486b744a7fe3799de8b35227bbb",
      "location": "Trollhättan",
      "company": "Siemens Energy AB",
      "country": "SE",
      "tier": "aggregator",
      "source": "jobtech"
    },
    {
      "title": "Projektspeditör till Siemens Energy",
      "url": "https://www.unikresurs.se/lediga-tjanster/?mtrpage=assignment&mtrt=ams&mtrid=9756",
      "location": "Finspång",
      "company": "UNIK Resurs i Sverige AB",
      "country": "SE",
      "tier": "aggregator",
      "source": "jobtech"
    },
    {
      "title": "Driftchef Teknik",
      "url": "https://iss.onecruiter.com/jobs/315930-driftchef-teknik?ref=platsbankenv2",
      "location": "Umeå",
      "company": "ISS FACILITY SERVICES AB",
      "country": "SE",
      "tier": "aggregator",
      "source": "jobtech"
    },
    {
      "title": "Laboratory Engineer – Materials Characterisation & R&D",
      "url": "https://axoconsulting.varbi.com/en/what:job/jobID:952418/type:job/where:125/apply:1",
      "location": "Hofors",
      "company": "AxÖ Consulting AB",
      "country": "SE",
      "tier": "aggregator",
      "source": "jobtech"
    },
    {
      "title": "Finance Controller",
      "url": "https://www.airliquide.com/join-us/careers-air-liquide",
      "location": "Stockholm",
      "company": "NORDICINFU CARE AB",
      "country": "SE",
      "tier": "aggregator",
      "source": "jobtech"
    },
    {
      "title": "IT/OT Security Engineer",
      "url": "https://hitachi.wd1.myworkdayjobs.com/hitachi/job/Ludvika-Dalarna-County-Sweden/IT-OT-Security-Engineer_R0103758",
      "location": "Ludvika",
      "company": "Hitachi Energy Sweden AB",
      "country": "SE",
      "tier": "aggregator",
      "source": "jobtech"
    },
    {
      "title": "Data Scientist till Savings Performance",
      "url": "https://jobs.swedbank.com/jobs/27275-data-scientist-till-savings-performance/applications/new?promotion=19171-arbetsformedlingen",
      "location": "Stockholm",
      "company": "Swedbank AB",
      "country": "SE",
      "tier": "aggregator",
      "source": "jobtech"
    },
    {
      "title": "Research engineer",
      "url": "https://arbetsformedlingen.se/platsbanken/annonser/31241870",
      "location": "",
      "company": "Farang AB",
      "country": "SE",
      "tier": "aggregator",
      "source": "jobtech"
    },
    {
      "title": "Solutions Engineer",
      "url": "https://jobs.ashbyhq.com/legora/2d5dd270-fa08-4c10-ae9c-1dd13da5beec",
      "location": "Stockholm",
      "company": "Legora AB",
      "country": "SE",
      "tier": "aggregator",
      "source": "jobtech"
    },
    {
      "title": "Legal Engineer, Government & Institutions",
      "url": "https://jobs.ashbyhq.com/legora/65c87ddc-3553-4641-b949-db84ef006a30",
      "location": "Stockholm",
      "company": "Legora AB",
      "country": "SE",
      "tier": "aggregator",
      "source": "jobtech"
    },
    {
      "title": "QA Test Engineer, Lund",
      "url": "https://www.aplitrak.com/?adid=eWx2YS5zdGFnbGVyLjE4ODU5LjEzNzY1QGF4aXNjb21tcy5hcGxpdHJhay5jb20",
      "location": "Lund",
      "company": "AXIS COMMUNICATIONS AKTIEBOLAG",
      "country": "SE",
      "tier": "aggregator",
      "source": "jobtech"
    },
    {
      "title": "AI Solutions Engineer",
      "url": "https://www.aplitrak.com/?adid=YS5vbHNzb24uNTE3MzAuMTM3NjVAc2FhYi5hcGxpdHJhay5jb20",
      "location": "Solna",
      "company": "SAAB AKTIEBOLAG",
      "country": "SE",
      "tier": "aggregator",
      "source": "jobtech"
    },
    {
      "title": "Legal Engineer - Tax & Audit",
      "url": "https://jobs.ashbyhq.com/legora/ab748e6a-84f9-4d9e-8e55-aac6fac7f1cc",
      "location": "Stockholm",
      "company": "Legora AB",
      "country": "SE",
      "tier": "aggregator",
      "source": "jobtech"
    },
    {
      "title": "Electronic Design Engineer, product development",
      "url": "https://flextronics.wd1.myworkdayjobs.com/en-US/Careers?Location_Country=6a800a4736884df5826858d435650f45&utm_source=Flex_Career_Site&utm_medium=button&utm_campaign=Sweden",
      "location": "Kalmar",
      "company": "FLEXTRONICS INTERNATIONAL SWEDEN AB",
      "country": "SE",
      "tier": "aggregator",
      "source": "jobtech"
    },
    {
      "title": "Product Owner ",
      "url": "https://www.aplitrak.com/?adid=VE1ITVMuMTY5NTMuMTM3NjVAdG95b3RhbWhlbWVhLmFwbGl0cmFrLmNvbQ",
      "location": "Mjölby",
      "company": "Toyota Material Handling Europe AB",
      "country": "SE",
      "tier": "aggregator",
      "source": "jobtech"
    },
    {
      "title": "Senior Java Developer with AWS",
      "url": "https://arbetsformedlingen.se/platsbanken/annonser/31243292",
      "location": "Göteborg",
      "company": "Surely Sci & Tech AB",
      "country": "SE",
      "tier": "aggregator",
      "source": "jobtech"
    },
    {
      "title": "Seniora mjukvaruutvecklare och arkitekter",
      "url": "www.pears.se",
      "location": "",
      "company": "We are Pears AB",
      "country": "SE",
      "tier": "aggregator",
      "source": "jobtech"
    },
    {
      "title": "Cloud Developer",
      "url": "https://hire.vismatalent.com/spa/public/apply?guidAssignment=a90242d3-ab06-4dba-a4c6-60cb3d750810&publishCode=PB&TK=fc918115-bb86-43da-baa9-7e3fa8f0bd2b",
      "location": "Växjö",
      "company": "Micropower Sweden AB",
      "country": "SE",
      "tier": "aggregator",
      "source": "jobtech"
    },
    {
      "title": "Senior Java Developer AWS Serverless",
      "url": "https://jobs.avaron.se/jobs/8011495-senior-java-developer-aws-serverless/applications/new?promotion=2083319-arbetsformedlingen",
      "location": "Göteborg",
      "company": "Avaron AB",
      "country": "SE",
      "tier": "aggregator",
      "source": "jobtech"
    },
    {
      "title": "Backend Engineer",
      "url": "https://www.ecommercerecruit.se/jobs/1097-backend-engineer/?pnty_src=platsbanken",
      "location": "Göteborg",
      "company": "E-commerce Recruit Nordic AB",
      "country": "SE",
      "tier": "aggregator",
      "source": "jobtech"
    },
    {
      "title": "Senior Fullstackutvecklare och Teknisk Lead",
      "url": "https://jobs.avaron.se/jobs/8010425-senior-fullstackutvecklare-och-teknisk-lead/applications/new?promotion=2082935-arbetsformedlingen",
      "location": "Stockholm",
      "company": "Avaron AB",
      "country": "SE",
      "tier": "aggregator",
      "source": "jobtech"
    },
    {
      "title": "Senior Software Developer",
      "url": "https://tfbank.teamtailor.com/jobs/7971212-senior-software-developer/applications/new?promotion=2082764-arbetsformedlingen",
      "location": "Västerås",
      "company": "Avarda Bank AB",
      "country": "SE",
      "tier": "aggregator",
      "source": "jobtech"
    },
    {
      "title": "GIS Software Developer",
      "url": "https://careers.navigraph.com/",
      "location": "Stockholm",
      "company": "Navigraph Kommanditbolag",
      "country": "SE",
      "tier": "aggregator",
      "source": "jobtech"
    },
    {
      "title": "Javautvecklare till Försäkringskassan, Sundsvall",
      "url": "https://go.talentech.io/l5487?utm_source=jobtip",
      "location": "Sundsvall",
      "company": "FÖRSÄKRINGSKASSAN",
      "country": "SE",
      "tier": "aggregator",
      "source": "jobtech"
    },
    {
      "title": "Javautvecklare till Försäkringskassan, Östersund",
      "url": "https://go.talentech.io/ZasCU?utm_source=jobtip",
      "location": "Östersund",
      "company": "FÖRSÄKRINGSKASSAN",
      "country": "SE",
      "tier": "aggregator",
      "source": "jobtech"
    },
    {
      "title": "Design Engineer",
      "url": "https://career.nextory.com/jobs/8006912-design-engineer/applications/new?promotion=2082207-arbetsformedlingen",
      "location": "Stockholm",
      "company": "Nextory AB",
      "country": "SE",
      "tier": "aggregator",
      "source": "jobtech"
    },
    {
      "title": "IT-supporttekniker till Mittuniversitetet - Östersund",
      "url": "https://miun.varbi.com/se/what:job/jobID:952797/type:job/where:125/apply:1",
      "location": "Östersund",
      "company": "MITTUNIVERSITETET",
      "country": "SE",
      "tier": "aggregator",
      "source": "jobtech"
    },
    {
      "title": "Senior Flutter Developer – Installer App",
      "url": "https://career.airahome.com/jobs/8005882-senior-flutter-developer-installer-app/applications/new?promotion=2081888-arbetsformedlingen",
      "location": "Stockholm",
      "company": "Aira Group AB",
      "country": "SE",
      "tier": "aggregator",
      "source": "jobtech"
    },
    {
      "title": "English and Spanish speaking Account Manager to Linköping",
      "url": "https://arbetsformedlingen.se/platsbanken/annonser/31230018",
      "location": "Linköping",
      "company": "TaxiCaller Nordic AB",
      "country": "SE",
      "tier": "aggregator",
      "source": "jobtech"
    },
    {
      "title": "Software Developer - Infotainment",
      "url": "https://careers.haleytek.com/jobs/7971849-software-developer-infotainment/applications/new?promotion=2083247-arbetsformedlingen",
      "location": "Göteborg",
      "company": "HaleyTek AB",
      "country": "SE",
      "tier": "aggregator",
      "source": "jobtech"
    },
    {
      "title": "Android & Embedded Developer",
      "url": "https://jobs.advantekgroup.com/job/481501",
      "location": "Göteborg",
      "company": "Avatron Digital West AB",
      "country": "SE",
      "tier": "aggregator",
      "source": "jobtech"
    },
    {
      "title": "Head of Governance & Digital Capabilities",
      "url": "https://www.aplitrak.com/?adid=cC5zdmVuc3Nvbi4xMDUwMy4xMzc2NUBzYWFiLmFwbGl0cmFrLmNvbQ",
      "location": "Solna",
      "company": "SAAB AKTIEBOLAG",
      "country": "SE",
      "tier": "aggregator",
      "source": "jobtech"
    },
    {
      "title": "Teknisk ledare Cloud & Infrastructure",
      "url": "https://www.aplitrak.com/?adid=ay5rYWhyZS44MTA2MC4xMzc2NUBzYWFiLmFwbGl0cmFrLmNvbQ",
      "location": "Lund",
      "company": "SAAB AKTIEBOLAG",
      "country": "SE",
      "tier": "aggregator",
      "source": "jobtech"
    },
    {
      "title": "Sales Manager",
      "url": "https://career.telavox.com/jobs/8002962-sales-manager?promotion=2083344-arbetsformedlingen",
      "location": "Malmö",
      "company": "Telavox AB",
      "country": "SE",
      "tier": "aggregator",
      "source": "jobtech"
    },
    {
      "title": "Principal Business Analyst",
      "url": "https://jobs.avaron.se/jobs/8011500-principal-business-analyst/applications/new?promotion=2083331-arbetsformedlingen",
      "location": "Eskilstuna",
      "company": "Avaron AB",
      "country": "SE",
      "tier": "aggregator",
      "source": "jobtech"
    },
    {
      "title": "Cloud Infrastructure Engineer",
      "url": "https://arbetsformedlingen.se/platsbanken/annonser/31242141",
      "location": "Malmö",
      "company": "Cloudist AB",
      "country": "SE",
      "tier": "aggregator",
      "source": "jobtech"
    },
    {
      "title": "Azure Cloud Engineer",
      "url": "https://career.accelerate-iver.com/jobs/8010610-azure-cloud-engineer/applications/new?promotion=2082921-arbetsformedlingen",
      "location": "Göteborg",
      "company": "Iver Accelerate AB",
      "country": "SE",
      "tier": "aggregator",
      "source": "jobtech"
    },
    {
      "title": "Kommunikatör",
      "url": "https://arbetsformedlingen.se/platsbanken/annonser/31241964",
      "location": "Sundsvall",
      "company": "ÅKERLUND VA OCH PLANERINGS AKTIEBOLAG",
      "country": "SE",
      "tier": "aggregator",
      "source": "jobtech"
    },
    {
      "title": "Redovisningsekonom med fokus på IFS Cloud till Väderstad",
      "url": "https://jobb.skill.se/jobs/7993373-redovisningsekonom-med-fokus-pa-ifs-cloud-till-vaderstad/applications/new?promotion=2082812-arbetsformedlingen",
      "location": "Mjölby",
      "company": "Skill Kompetenspartner AB",
      "country": "SE",
      "tier": "aggregator",
      "source": "jobtech"
    },
    {
      "title": "Site Reliability Engineer/Cloud Engineer",
      "url": "https://career.accelerate-iver.com/jobs/8009703-site-reliability-engineer-cloud-engineer/applications/new?promotion=2082517-arbetsformedlingen",
      "location": "Malmö",
      "company": "Iver Accelerate AB",
      "country": "SE",
      "tier": "aggregator",
      "source": "jobtech"
    },
    {
      "title": "CRM Manager till Svea Solar - Konsultuppdrag",
      "url": "https://karriar.digitalenta.se/jobs/8008922-crm-manager-till-svea-solar-konsultuppdrag/applications/new?promotion=2082401-arbetsformedlingen",
      "location": "Stockholm",
      "company": "Digitalenta AB",
      "country": "SE",
      "tier": "aggregator",
      "source": "jobtech"
    },
    {
      "title": "Tech Lead – Careium Malmö",
      "url": "https://karriar.careium.com/jobs/rm?rmpage=job&rmjob=581&utm_medium=talentech_publishing&utm_source=jobtip",
      "location": "Malmö",
      "company": "Careium Sweden AB",
      "country": "SE",
      "tier": "aggregator",
      "source": "jobtech"
    }
  ]
}